isensing/__init__.py
isensing/anomaly/__init__.py
isensing/anomaly/alphahull.py
isensing/anomaly/hdr.py
isensing/anomaly/outlier_detection.py
isensing/decomposition/__init__.py
isensing/decomposition/robpca.py
isensing/features_extraction/__init__.py
isensing/features_extraction/timeseries.py
isensing-0.1.1.dist-info/LICENSE
isensing-0.1.1.dist-info/METADATA
isensing-0.1.1.dist-info/WHEEL
isensing-0.1.1.dist-info/top_level.txt
isensing-0.1.1.dist-info/RECORD
