Metadata-Version: 2.1
Name: isensing
Version: 0.1.1
Summary: Intelligent Sensing Toolbox for Multivariate Time Series
Home-page: https://gitlab.com/imda-dsl/intelligent-sensing-toolbox
Author: IMDA Digital Services Lab
License: UNKNOWN
Platform: UNKNOWN
Classifier: Programming Language :: Python :: 3
Classifier: License :: OSI Approved :: Apache Software License
Classifier: Operating System :: OS Independent
Classifier: Environment :: Console
Requires-Dist: pandas
Requires-Dist: numpy
Requires-Dist: statsmodels
Requires-Dist: scipy
Requires-Dist: fastdtw
Requires-Dist: sklearn
Requires-Dist: matplotlib
Requires-Dist: plotly
Requires-Dist: descartes
Requires-Dist: shapely
